GaussParse/__init__.py
GaussParse/app.py
GaussParse/config/__init__.py
GaussParse/config/constants.py
GaussParse/data/periodic_table.json
GaussParse/docs/__init__.py
GaussParse/docs/irc_result.py
GaussParse/docs/manager.py
GaussParse/docs/nbo_analysis.py
GaussParse/docs/nbo_parser.py
GaussParse/docs/plot_result.py
GaussParse/docs/structure.py
GaussParse/docs/summary_result.py
GaussParse/handlers/__init__.py
GaussParse/handlers/errors.py
GaussParse/parsers/__init__.py
GaussParse/parsers/parser_directionality.py
GaussParse/parsers/parser_natural_atomic_orbital_occupancies.py
GaussParse/parsers/parser_natural_orbital_analysis.py
GaussParse/parsers/parser_natural_population_analysis.py
GaussParse/parsers/parser_nbo_summary.py
GaussParse/parsers/parser_occupacy.py
GaussParse/parsers/parser_second_order_perturbation.py
GaussParse/templates/BOND_ORBITAL_COEFFICIENTS_HYBRIDS.html
GaussParse/templates/NATURAL_ATOMIC_ORBITAL_ACCUPACIES.html
GaussParse/templates/NATURAL_BOND_ORBITALS_SUMMARY.html
GaussParse/templates/NATURAL_BOND_ORBITAL_ANALYSIS.html
GaussParse/templates/NHO_DIRECTIONALITY_BOND_BENDING.html
GaussParse/templates/SECOND_ORDER_PERTURBATION_THEORY_ANALYSIS.html
GaussParse/templates/SUMMARY_OF_NATURAL_POPULATION_ANALYSIS.html
GaussParse/templates/nbo.html
GaussParse/utils/__init__.py
GaussParse/utils/appmanager.py
GaussParse/utils/converter.py
gaussparse-1.3.7.dist-info/licenses/LICENSE
gaussparse-1.3.7.dist-info/METADATA
gaussparse-1.3.7.dist-info/WHEEL
gaussparse-1.3.7.dist-info/top_level.txt
gaussparse-1.3.7.dist-info/RECORD
