Metadata-Version: 2.4
Name: GaussParse
Version: 1.3.7
Summary: GaussParse is a python package to parse Gaussian output files.
Author: Sina Gilassi
Author-email: <sina.gilassi@gmail.com>
License: MIT
Keywords: Python,Gaussian Software,Computational Chemistry,Gaussian Parser,Reaction Energy Profile
Classifier: Development Status :: 1 - Planning
Classifier: Intended Audience :: Education
Classifier: Programming Language :: Python :: 3
Classifier: Operating System :: Unix
Classifier: Operating System :: MacOS :: MacOS X
Classifier: Operating System :: Microsoft :: Windows
Requires-Python: >=3.10
License-File: LICENSE
Requires-Dist: pandas
Requires-Dist: numpy
Requires-Dist: openpyxl
Requires-Dist: xlsxwriter
Requires-Dist: jinja2
Requires-Dist: rich
Provides-Extra: plotting
Requires-Dist: matplotlib; extra == "plotting"
Dynamic: author
Dynamic: author-email
Dynamic: classifier
Dynamic: description
Dynamic: description-content-type
Dynamic: keywords
Dynamic: license
Dynamic: license-file
Dynamic: provides-extra
Dynamic: requires-dist
Dynamic: requires-python
Dynamic: summary
